serverhttpy/__init__.py
serverhttpy/client.py
serverhttpy/server.py
serverhttpy/enums/__init__.py
serverhttpy/enums/http_method.py
serverhttpy/enums/status_code.py
serverhttpy/examples/example_clients_managment.py
serverhttpy/examples/sample_data.py
serverhttpy/exceptions/__init__.py
serverhttpy/exceptions/invalid_header_structure.py
serverhttpy/exceptions/invalid_path_structure.py
serverhttpy/exceptions/invalid_query_param_structure.py
serverhttpy/exceptions/invalid_request_structure.py
serverhttpy/exceptions/no_action_registered_in_endpoint.py
serverhttpy/exceptions/unsupported_method_specified.py
serverhttpy/models/__init__.py
serverhttpy/models/endpoint.py
serverhttpy/models/path.py
serverhttpy/models/request.py
serverhttpy/models/response.py
serverhttpy/models/uri.py
serverhttpy-0.0.4.dist-info/METADATA
serverhttpy-0.0.4.dist-info/WHEEL
serverhttpy-0.0.4.dist-info/top_level.txt
serverhttpy-0.0.4.dist-info/RECORD
