Metadata-Version: 2.1
Name: serverhttpy
Version: 0.0.4
Summary: Simple web server framework for Python
Home-page: https://github.com/bastyje/serverhttpy
Author: Sebastian Górka, Michał Ziober
Requires-Python: >=3.10
